dirichlet/__init__.py
dirichlet/dirichlet.py
dirichlet/simplex.py
dirichlet-1.0.0.dist-info/WHEEL
dirichlet-1.0.0.dist-info/METADATA
dirichlet-1.0.0.dist-info/RECORD
