Metadata-Version: 2.3
Name: dirichlet
Version: 1.0.0
Summary: Calculates Dirichlet test and plots 2-simplex Dirichlets
Author: Eric Suh
Author-email: Eric Suh <contact@ericsuh.com>
License: MIT
Classifier: Programming Language :: Python
Classifier: Programming Language :: Python :: 3
Classifier: Programming Language :: Python :: 3.8
Classifier: Programming Language :: Python :: 3.9
Classifier: Programming Language :: Python :: 3.10
Classifier: Programming Language :: Python :: 3.11
Classifier: Programming Language :: Python :: 3.12
Classifier: License :: OSI Approved :: MIT License
Classifier: Operating System :: OS Independent
Classifier: Development Status :: 4 - Beta
Classifier: Intended Audience :: Developers
Classifier: Intended Audience :: Science/Research
Classifier: Topic :: Scientific/Engineering
Classifier: Topic :: Scientific/Engineering :: Information Analysis
Requires-Dist: scipy>=1.4.1
Requires-Dist: numpy>=1.18.1
Requires-Dist: matplotlib>=3.2.0 ; extra == 'simplex'
Maintainer: Eric Suh
Maintainer-email: Eric Suh <contact@ericsuh.com>
Requires-Python: >=3.10
Project-URL: Bug Tracker, https://github.com/ericsuh/dirichlet/issues
Project-URL: Homepage, http://github.com/ericsuh/dirichlet
Project-URL: Repository, https://github.com/ericsuh/dirichlet
Provides-Extra: simplex
